pencilpycommons/__init__.py
pencilpycommons/aws/__init__.py
pencilpycommons/aws/manager.py
pencilpycommons/aws/resource.py
pencilpycommons/cache/__init__.py
pencilpycommons/cache/abstract.py
pencilpycommons/cache/config.py
pencilpycommons/cache/redis_connection.py
pencilpycommons/cache/redis_manager.py
pencilpycommons/db/__init__.py
pencilpycommons/db/abstract.py
pencilpycommons/db/config.py
pencilpycommons/db/dynamo_client.py
pencilpycommons/db/mysql_client.py
pencilpycommons/mq/__init__.py
pencilpycommons/mq/amqp_consumer.py
pencilpycommons/mq/amqp_manager.py
pencilpycommons/serverless/__init__.py
pencilpycommons/serverless/abstract.py
pencilpycommons/serverless/aws_lambda.py
pencilpycommons/serverless/exceptions.py
pencilpycommons/storage/__init__.py
pencilpycommons/storage/abstract.py
pencilpycommons/storage/exceptions.py
pencilpycommons/storage/s3_manager.py
pencilpycommons/storage/utils.py
pencilpycommons-0.0.8.dist-info/LICENSE.txt
pencilpycommons-0.0.8.dist-info/METADATA
pencilpycommons-0.0.8.dist-info/WHEEL
pencilpycommons-0.0.8.dist-info/top_level.txt
pencilpycommons-0.0.8.dist-info/RECORD
