Metadata-Version: 2.1
Name: pencilpycommons
Version: 0.0.8
Summary: Commons library
Home-page: UNKNOWN
Author: Abhinav
Author-email: abhinav@trypencil.com
License: MIT
Platform: UNKNOWN
Classifier: Programming Language :: Python :: 3
Classifier: License :: OSI Approved :: MIT License
Classifier: Operating System :: OS Independent
License-File: LICENSE.txt
Requires-Dist: boto3 (==1.11.8)
Requires-Dist: redis (==3.5.3)
Requires-Dist: peewee (==3.13.1)
Requires-Dist: PyMySQL (==0.9.3)
Requires-Dist: pika (==0.13.1)
Requires-Dist: requests (==2.26.0)
